lens/__init__.py
lens/lens_score.py
lens/encoders/__init__.py
lens/encoders/base.py
lens/encoders/bert.py
lens/encoders/roberta.py
lens/models/__init__.py
lens/models/base.py
lens/models/lru_cache.py
lens/models/metrics.py
lens/models/pooling_utils.py
lens/models/predict_pbar.py
lens/models/predict_writer.py
lens/models/regression_metric_multi_ref.py
lens/models/unified_metric.py
lens/models/utils.py
lens/modules/__init__.py
lens/modules/feedforward.py
lens/modules/layerwise_attention.py
lens_metric-0.2.0.dist-info/LICENSE
lens_metric-0.2.0.dist-info/METADATA
lens_metric-0.2.0.dist-info/WHEEL
lens_metric-0.2.0.dist-info/top_level.txt
lens_metric-0.2.0.dist-info/RECORD
