Metadata-Version: 2.1
Name: lens_metric
Version: 0.2.0
Summary: A learnable evaluation metric for text simplification
Home-page: https://github.com/Yao-Dou/LENS
Download-URL: https://github.com/Yao-Dou/LENS/archive/refs/tags/v0.2.0.tar.gz
Author: Mounica Maddela
Author-email: mmaddela3@gatech.edu
License: Apache license
Classifier: Development Status :: 5 - Production/Stable 
Classifier: Intended Audience :: Science/Research
License-File: LICENSE
Requires-Dist: sentencepiece >=0.1.96
Requires-Dist: pandas <2.0.0,>=1.5.0
Requires-Dist: transformers >=4.8
Requires-Dist: pytorch-lightning ==2.0.9
Requires-Dist: jsonargparse ==3.13.1
Requires-Dist: torch >=2.0.1
Requires-Dist: numpy >=1.20.0
Requires-Dist: torchmetrics >=0.7
Requires-Dist: sacrebleu >=2.0.0
Requires-Dist: scipy >=1.5.4
